<annotation>
	<folder>train</folder>
	<filename>IMG_1364.JPEG</filename>
	<path>/home/shen42/Desktop/training 2/train/IMG_1364.JPEG</path>
	<source>
		<database>Unknown</database>
	</source>
	<size>
		<width>2048</width>
		<height>1536</height>
		<depth>3</depth>
	</size>
	<segmented>0</segmented>
	<object>
		<name>No</name>
		<pose>Unspecified</pose>
		<truncated>0</truncated>
		<difficult>0</difficult>
		<bndbox>
			<xmin>161</xmin>
			<ymin>725</ymin>
			<xmax>1017</xmax>
			<ymax>1233</ymax>
		</bndbox>
	</object>
</annotation>
